[
  {
    "serialNumber": 2,
    "metadataTokenId": 1,
    "hederaTokenId": "0.0.10175359",
    "rarity": "common",
    "tierName": "Common Warrior",
    "odinAllocation": 40000,
    "ownerAccountId": "0.0.10174943",
    "mintTransactionId": "0.0.10096557@1765406191.888774270",
    "paymentTransactionHash": "0.0.10174943@1765406178.427691564",
    "paidAmount": 0.74073398,
    "paidCurrency": "HBAR",
    "hbarUsdRate": 0.135533,
    "metadataUri": "https://min.theninerealms.world/metadata/1.json",
    "ipfsGatewayUrl": null,
    "mintedAt": "2025-12-10T22:36:47.821Z",
    "timestamp": 1765406207822,
    "isAirdrop": false,
    "mintType": "public_mint"
  },
  {
    "serialNumber": 3,
    "metadataTokenId": 3,
    "hederaTokenId": "0.0.10175359",
    "rarity": "legendary",
    "tierName": "Legendary Hero",
    "odinAllocation": 1000000,
    "ownerAccountId": "0.0.10174943",
    "mintTransactionId": "0.0.10096557@1765406381.748030645",
    "paymentTransactionHash": "0.0.10174943@1765406375.634964595",
    "paidAmount": 4.44073398,
    "paidCurrency": "HBAR",
    "hbarUsdRate": 0.135533,
    "metadataUri": "https://min.theninerealms.world/metadata/3.json",
    "ipfsGatewayUrl": null,
    "mintedAt": "2025-12-10T22:40:13.692Z",
    "timestamp": 1765406413693,
    "isAirdrop": false,
    "mintType": "public_mint"
  },
  {
    "serialNumber": 4,
    "metadataTokenId": 24,
    "hederaTokenId": "0.0.10175359",
    "rarity": "legendary",
    "tierName": "Legendary Hero",
    "odinAllocation": 1000000,
    "ownerAccountId": "0.0.10174943",
    "mintTransactionId": "0.0.10096557@1765406393.322075647",
    "paymentTransactionHash": "0.0.10174943@1765406375.634964595",
    "paidAmount": 4.44073398,
    "paidCurrency": "HBAR",
    "hbarUsdRate": 0.135533,
    "metadataUri": "https://min.theninerealms.world/metadata/24.json",
    "ipfsGatewayUrl": null,
    "mintedAt": "2025-12-10T22:40:15.502Z",
    "timestamp": 1765406415502,
    "isAirdrop": false,
    "mintType": "public_mint"
  },
  {
    "serialNumber": 5,
    "metadataTokenId": 5,
    "hederaTokenId": "0.0.10175359",
    "rarity": "rare",
    "tierName": "Rare Champion",
    "odinAllocation": 300000,
    "ownerAccountId": "0.0.10174943",
    "mintTransactionId": "0.0.10096557@1765406466.027346601",
    "paymentTransactionHash": "0.0.10174943@1765406458.925041736",
    "paidAmount": 4.44073397,
    "paidCurrency": "HBAR",
    "hbarUsdRate": 0.13577,
    "metadataUri": "https://min.theninerealms.world/metadata/5.json",
    "ipfsGatewayUrl": null,
    "mintedAt": "2025-12-10T22:41:48.151Z",
    "timestamp": 1765406508151,
    "isAirdrop": false,
    "mintType": "public_mint"
  },
  {
    "serialNumber": 6,
    "metadataTokenId": 9,
    "hederaTokenId": "0.0.10175359",
    "rarity": "rare",
    "tierName": "Rare Champion",
    "odinAllocation": 300000,
    "ownerAccountId": "0.0.10174943",
    "mintTransactionId": "0.0.10096557@1765406477.662582708",
    "paymentTransactionHash": "0.0.10174943@1765406458.925041736",
    "paidAmount": 4.44073397,
    "paidCurrency": "HBAR",
    "hbarUsdRate": 0.13577,
    "metadataUri": "https://min.theninerealms.world/metadata/9.json",
    "ipfsGatewayUrl": null,
    "mintedAt": "2025-12-10T22:41:50.239Z",
    "timestamp": 1765406510239,
    "isAirdrop": false,
    "mintType": "public_mint"
  },
  {
    "serialNumber": 7,
    "metadataTokenId": 12,
    "hederaTokenId": "0.0.10175359",
    "rarity": "rare",
    "tierName": "Rare Champion",
    "odinAllocation": 300000,
    "ownerAccountId": "0.0.10174943",
    "mintTransactionId": "0.0.10096557@1765406494.731228504",
    "paymentTransactionHash": "0.0.10174943@1765406458.925041736",
    "paidAmount": 4.44073397,
    "paidCurrency": "HBAR",
    "hbarUsdRate": 0.13577,
    "metadataUri": "https://min.theninerealms.world/metadata/12.json",
    "ipfsGatewayUrl": null,
    "mintedAt": "2025-12-10T22:41:52.332Z",
    "timestamp": 1765406512332,
    "isAirdrop": false,
    "mintType": "public_mint"
  },
  {
    "serialNumber": 8,
    "metadataTokenId": 13,
    "hederaTokenId": "0.0.10175359",
    "rarity": "rare",
    "tierName": "Rare Champion",
    "odinAllocation": 300000,
    "ownerAccountId": "0.0.10174943",
    "mintTransactionId": "0.0.10096557@1765408092.318939539",
    "paymentTransactionHash": "0.0.10174943@1765408082.079700119",
    "paidAmount": 1.47074348,
    "paidCurrency": "HBAR",
    "hbarUsdRate": 0.136166,
    "metadataUri": "https://min.theninerealms.world/metadata/13.json",
    "ipfsGatewayUrl": null,
    "mintedAt": "2025-12-10T23:08:29.573Z",
    "timestamp": 1765408109574,
    "isAirdrop": false,
    "mintType": "public_mint"
  },
  {
    "serialNumber": 9,
    "metadataTokenId": 2,
    "hederaTokenId": "0.0.10175359",
    "rarity": "common",
    "tierName": "Common Warrior",
    "odinAllocation": 40000,
    "ownerAccountId": "0.0.10168171",
    "mintTransactionId": "0.0.10096557@1765408374.273110832",
    "paymentTransactionHash": null,
    "paidAmount": null,
    "paidCurrency": "AIRDROP",
    "hbarUsdRate": null,
    "metadataUri": "https://min.theninerealms.world/metadata/2.json",
    "ipfsGatewayUrl": null,
    "mintedAt": "2025-12-10T23:13:11.407Z",
    "timestamp": 1765408391407,
    "isAirdrop": true,
    "mintType": "airdrop"
  },
  {
    "serialNumber": 10,
    "metadataTokenId": 4,
    "hederaTokenId": "0.0.10175359",
    "rarity": "common",
    "tierName": "Common Warrior",
    "odinAllocation": 40000,
    "ownerAccountId": "0.0.10174943",
    "mintTransactionId": "0.0.10096557@1765408388.236660407",
    "paymentTransactionHash": null,
    "paidAmount": null,
    "paidCurrency": "AIRDROP",
    "hbarUsdRate": null,
    "metadataUri": "https://min.theninerealms.world/metadata/4.json",
    "ipfsGatewayUrl": null,
    "mintedAt": "2025-12-10T23:13:23.560Z",
    "timestamp": 1765408403560,
    "isAirdrop": true,
    "mintType": "airdrop"
  },
  {
    "serialNumber": 11,
    "metadataTokenId": 16,
    "hederaTokenId": "0.0.10175359",
    "rarity": "rare",
    "tierName": "Rare Champion",
    "odinAllocation": 300000,
    "ownerAccountId": "0.0.10174943",
    "mintTransactionId": "0.0.10096557@1765408558.878930426",
    "paymentTransactionHash": null,
    "paidAmount": null,
    "paidCurrency": "AIRDROP",
    "hbarUsdRate": null,
    "metadataUri": "https://min.theninerealms.world/metadata/16.json",
    "ipfsGatewayUrl": null,
    "mintedAt": "2025-12-10T23:16:17.860Z",
    "timestamp": 1765408577860,
    "isAirdrop": true,
    "mintType": "airdrop"
  },
  {
    "serialNumber": 12,
    "metadataTokenId": 20,
    "hederaTokenId": "0.0.10175359",
    "rarity": "rare",
    "tierName": "Rare Champion",
    "odinAllocation": 300000,
    "ownerAccountId": "0.0.10168171",
    "mintTransactionId": "0.0.10096557@1765408576.209967773",
    "paymentTransactionHash": null,
    "paidAmount": null,
    "paidCurrency": "AIRDROP",
    "hbarUsdRate": null,
    "metadataUri": "https://min.theninerealms.world/metadata/20.json",
    "ipfsGatewayUrl": null,
    "mintedAt": "2025-12-10T23:16:28.416Z",
    "timestamp": 1765408588416,
    "isAirdrop": true,
    "mintType": "airdrop"
  },
  {
    "serialNumber": 13,
    "metadataTokenId": 48,
    "hederaTokenId": "0.0.10175359",
    "rarity": "legendary",
    "tierName": "Legendary Hero",
    "odinAllocation": 1000000,
    "ownerAccountId": "0.0.10168171",
    "mintTransactionId": "0.0.10096557@1765408715.575977955",
    "paymentTransactionHash": null,
    "paidAmount": null,
    "paidCurrency": "AIRDROP",
    "hbarUsdRate": null,
    "metadataUri": "https://min.theninerealms.world/metadata/48.json",
    "ipfsGatewayUrl": null,
    "mintedAt": "2025-12-10T23:18:52.271Z",
    "timestamp": 1765408732271,
    "isAirdrop": true,
    "mintType": "airdrop"
  },
  {
    "serialNumber": 14,
    "metadataTokenId": 27,
    "hederaTokenId": "0.0.10175359",
    "rarity": "rare",
    "tierName": "Rare Champion",
    "odinAllocation": 300000,
    "ownerAccountId": "0.0.10174943",
    "mintTransactionId": "0.0.10096557@1765408852.004394595",
    "paymentTransactionHash": "0.0.10174943@1765408840.752163429",
    "paidAmount": 2.96074348,
    "paidCurrency": "HBAR",
    "hbarUsdRate": 0.13585,
    "metadataUri": "https://min.theninerealms.world/metadata/27.json",
    "ipfsGatewayUrl": null,
    "mintedAt": "2025-12-10T23:21:22.930Z",
    "timestamp": 1765408882930,
    "isAirdrop": false,
    "mintType": "public_mint"
  },
  {
    "serialNumber": 15,
    "metadataTokenId": 28,
    "hederaTokenId": "0.0.10175359",
    "rarity": "rare",
    "tierName": "Rare Champion",
    "odinAllocation": 300000,
    "ownerAccountId": "0.0.10174943",
    "mintTransactionId": "0.0.10096557@1765408864.972794500",
    "paymentTransactionHash": "0.0.10174943@1765408840.752163429",
    "paidAmount": 2.96074348,
    "paidCurrency": "HBAR",
    "hbarUsdRate": 0.13585,
    "metadataUri": "https://min.theninerealms.world/metadata/28.json",
    "ipfsGatewayUrl": null,
    "mintedAt": "2025-12-10T23:21:24.707Z",
    "timestamp": 1765408884707,
    "isAirdrop": false,
    "mintType": "public_mint"
  },
  {
    "serialNumber": 16,
    "metadataTokenId": 70,
    "hederaTokenId": "0.0.10175359",
    "rarity": "legendary",
    "tierName": "Legendary Hero",
    "odinAllocation": 1000000,
    "ownerAccountId": "0.0.10174943",
    "mintTransactionId": "0.0.10096557@1765410197.070922684",
    "paymentTransactionHash": "0.0.10174943@1765410187.323221516",
    "paidAmount": 2.23074348,
    "paidCurrency": "HBAR",
    "hbarUsdRate": 0.135078,
    "metadataUri": "https://min.theninerealms.world/metadata/70.json",
    "ipfsGatewayUrl": null,
    "mintedAt": "2025-12-10T23:43:35.330Z",
    "timestamp": 1765410215330,
    "isAirdrop": false,
    "mintType": "public_mint"
  },
  {
    "serialNumber": 17,
    "metadataTokenId": 6,
    "hederaTokenId": "0.0.10175359",
    "rarity": "common",
    "tierName": "Common Warrior",
    "odinAllocation": 40000,
    "ownerAccountId": "0.0.10174943",
    "mintTransactionId": "0.0.10096557@1765410328.474668629",
    "paymentTransactionHash": "0.0.10174943@1765410319.639252750",
    "paidAmount": 4.29074348,
    "paidCurrency": "HBAR",
    "hbarUsdRate": 0.07,
    "metadataUri": "https://min.theninerealms.world/metadata/6.json",
    "ipfsGatewayUrl": null,
    "mintedAt": "2025-12-10T23:46:08.439Z",
    "timestamp": 1765410368439,
    "isAirdrop": false,
    "mintType": "public_mint"
  },
  {
    "serialNumber": 18,
    "metadataTokenId": 7,
    "hederaTokenId": "0.0.10175359",
    "rarity": "common",
    "tierName": "Common Warrior",
    "odinAllocation": 40000,
    "ownerAccountId": "0.0.10174943",
    "mintTransactionId": "0.0.10096557@1765410340.837381701",
    "paymentTransactionHash": "0.0.10174943@1765410319.639252750",
    "paidAmount": 4.29074348,
    "paidCurrency": "HBAR",
    "hbarUsdRate": 0.07,
    "metadataUri": "https://min.theninerealms.world/metadata/7.json",
    "ipfsGatewayUrl": null,
    "mintedAt": "2025-12-10T23:46:09.139Z",
    "timestamp": 1765410369139,
    "isAirdrop": false,
    "mintType": "public_mint"
  },
  {
    "serialNumber": 19,
    "metadataTokenId": 8,
    "hederaTokenId": "0.0.10175359",
    "rarity": "common",
    "tierName": "Common Warrior",
    "odinAllocation": 40000,
    "ownerAccountId": "0.0.10174943",
    "mintTransactionId": "0.0.10096557@1765410353.750364809",
    "paymentTransactionHash": "0.0.10174943@1765410319.639252750",
    "paidAmount": 4.29074348,
    "paidCurrency": "HBAR",
    "hbarUsdRate": 0.07,
    "metadataUri": "https://min.theninerealms.world/metadata/8.json",
    "ipfsGatewayUrl": null,
    "mintedAt": "2025-12-10T23:46:09.761Z",
    "timestamp": 1765410369761,
    "isAirdrop": false,
    "mintType": "public_mint"
  },
  {
    "serialNumber": 20,
    "metadataTokenId": 31,
    "hederaTokenId": "0.0.10175359",
    "rarity": "rare",
    "tierName": "Rare Champion",
    "odinAllocation": 300000,
    "ownerAccountId": "0.0.10174943",
    "mintTransactionId": "0.0.10096557@1765410417.770110297",
    "paymentTransactionHash": "0.0.10174943@1765410410.378091042",
    "paidAmount": 1.49074348,
    "paidCurrency": "HBAR",
    "hbarUsdRate": 0.135084,
    "metadataUri": "https://min.theninerealms.world/metadata/31.json",
    "ipfsGatewayUrl": null,
    "mintedAt": "2025-12-10T23:47:15.293Z",
    "timestamp": 1765410435293,
    "isAirdrop": false,
    "mintType": "public_mint"
  }
]